mcp_refactoring_assistant/__init__.py
mcp_refactoring_assistant/server.py
mcp_python_refactoring-0.1.0.dist-info/METADATA
mcp_python_refactoring-0.1.0.dist-info/WHEEL
mcp_python_refactoring-0.1.0.dist-info/entry_points.txt
mcp_python_refactoring-0.1.0.dist-info/licenses/LICENSE
mcp_python_refactoring-0.1.0.dist-info/RECORD
