Metadata-Version: 2.4
Name: mcp-python-refactoring
Version: 0.1.0
Summary: MCP tool to guide Python code refactoring without automatic changes
Project-URL: Homepage, https://github.com/slamer59/mcp-python-refactoring
Project-URL: Repository, https://github.com/slamer59/mcp-python-refactoring
Project-URL: Issues, https://github.com/slamer59/mcp-python-refactoring/issues
Author-email: slamer59 <your.email@example.com>
License: MIT
License-File: LICENSE
Keywords: ai-assistant,code-analysis,mcp,python,refactoring
Classifier: Development Status :: 4 - Beta
Classifier: Intended Audience :: Developers
Classifier: License :: OSI Approved :: MIT License
Classifier: Programming Language :: Python :: 3
Classifier: Programming Language :: Python :: 3.13
Classifier: Topic :: Software Development :: Code Generators
Classifier: Topic :: Software Development :: Quality Assurance
Requires-Python: >=3.13
Requires-Dist: fastapi>=0.104.0
Requires-Dist: jedi>=0.19.1
Requires-Dist: libcst>=1.1.0
Requires-Dist: mccabe>=0.7.0
Requires-Dist: mcp>=1.13.1
Requires-Dist: radon>=6.0.1
Requires-Dist: rope>=1.11.0
Requires-Dist: uvicorn>=0.24.0
Requires-Dist: vulture>=2.10
Provides-Extra: mcp
Requires-Dist: mcp>=1.0.0; extra == 'mcp'
